PlacasRegPY/Modulos.py
PlacasRegPY/__init__.py
PlacasRegPY/main.py
PlacasRegPY-1.2.2.dist-info/LICENSE
PlacasRegPY-1.2.2.dist-info/METADATA
PlacasRegPY-1.2.2.dist-info/WHEEL
PlacasRegPY-1.2.2.dist-info/top_level.txt
PlacasRegPY-1.2.2.dist-info/RECORD
