Metadata-Version: 2.1
Name: PlacasRegPY
Version: 1.2.2
Summary: Este es un pequeño código de un programa para hacer identificación de matrículas vehiculares, para conocer a que tipo de vehículo/entidad le pertenece dicha matricula.
Home-page: https://github.com/LightKnight23/RegMatriculasPy
Author: Eyvar García
Author-email: eyvar.0823@gmail.com
License: UNKNOWN
Platform: UNKNOWN
Classifier: Programming Language :: Python :: 3
Classifier: License :: OSI Approved :: MIT License
Classifier: Operating System :: OS Independent
